README.md
setup.py
face_recognize/__init__.py
face_recognize/__main__.py
face_recognize/common.py
face_recognize/database.py
face_recognize/detector.py
face_recognize/recognizer.py
face_recognize/utils.py
face_recognize.egg-info/PKG-INFO
face_recognize.egg-info/SOURCES.txt
face_recognize.egg-info/dependency_links.txt
face_recognize.egg-info/entry_points.txt
face_recognize.egg-info/requires.txt
face_recognize.egg-info/top_level.txt
face_recognize/backends/__init__.py
face_recognize/backends/arcsoft_v1/AFD_FSDKLibrary.py
face_recognize/backends/arcsoft_v1/AFR_FSDKLibrary.py
face_recognize/backends/arcsoft_v1/AFT_FSDKLibrary.py
face_recognize/backends/arcsoft_v1/ASVL_COLOR_FORMAT.py
face_recognize/backends/arcsoft_v1/__init__.py
face_recognize/backends/arcsoft_v1/face_api.py
face_recognize/backends/arcsoft_v3/__init__.py
face_recognize/backends/arcsoft_v3/arcsoft_face_sdk.py
face_recognize/backends/arcsoft_v3/asvloffscreen.py
face_recognize/backends/arcsoft_v3/face_api.py
face_recognize/backends/arcsoft_v3/merror.py
face_recognize/backends/dlib_soa/__init__.py
face_recognize/backends/dlib_soa/face_api.py